MANIFEST.in
README.rst
setup.py
sparql.py
version.txt
docs/HISTORY.txt
docs/api.rst
docs/conf.py
docs/index.rst
sparql_client.egg-info/PKG-INFO
sparql_client.egg-info/SOURCES.txt
sparql_client.egg-info/dependency_links.txt
sparql_client.egg-info/requires.txt
sparql_client.egg-info/top_level.txt