Metadata-Version: 2.1
Name: sparql-client
Version: 3.7
Summary: Python API to query a SPARQL endpoint
Home-page: https://github.com/eea/sparql-client
Author: European Environment Agency: IDM2 A-Team
Author-email: eea-edw-a-team-alerts@googlegroups.com
License: MPL
Keywords: Sparql Client
Platform: UNKNOWN
Classifier: Environment :: Console
Classifier: Intended Audience :: Developers
Classifier: Programming Language :: Python
Classifier: Operating System :: OS Independent
Classifier: Topic :: Software Development :: Libraries :: Python Modules
Provides-Extra: test
